MANIFEST.in
README.md
setup.cfg
setup.py
setupint3/__init__.py
setupint3.egg-info/PKG-INFO
setupint3.egg-info/SOURCES.txt
setupint3.egg-info/dependency_links.txt
setupint3.egg-info/top_level.txt