Metadata-Version: 2.1
Name: setupint3
Version: 0.0.2
Summary: by myeggs, myeggs and myeggs
Author-email: <myeggs@gmail.com>
License: Eclipse Public License 2.0
Keywords: setupint3,colorama
